{
  "timestamp": "2026-07-22",
  "strategy": "V4.1 (科技7族群+市值100億+美股加分+0050體制+7日黑名單)",
  "strongest_industry": "電腦及週邊",
  "v4_blocked": false,
  "picks": [
    {
      "today": 5500.0,
      "monthly_max_2y": 5291.7421875,
      "ratio": 1.0393552454221864,
      "from_high_pct": 3.935524542218638,
      "bullish": false,
      "bullish_fast": false,
      "change_pct": 10.000000000000009,
      "vol_ratio": 2.248706248756179,
      "rsi": 57.21153846153846,
      "ma5": 4984.0,
      "ma20": 4930.0,
      "ma60": 4981.801928710937,
      "ma200": 4202.513153076172,
      "gap_up": true,
      "close_near_high": true,
      "long_red": true,
      "ticker": "6669",
      "name": "緯穎",
      "industry": "電腦及週邊",
      "industry_strong": true,
      "market_cap_billions": 9236.2866688,
      "mcap_pass": true,
      "momentum_score": 95,
      "momentum_notes": [
        "跳空缺口",
        "ATH",
        "族群同步"
      ],
      "tier": "⭐⭐⭐",
      "next_day_prob": "≥85%"
    },
    {
      "today": 490.0,
      "monthly_max_2y": 369.5,
      "ratio": 1.3261163734776726,
      "from_high_pct": 32.611637347767264,
      "bullish": true,
      "bullish_fast": true,
      "change_pct": 9.988776655443331,
      "vol_ratio": 2.604257672037812,
      "rsi": 82.45125348189416,
      "ma5": 427.1,
      "ma20": 392.8,
      "ma60": 363.32752126057943,
      "ma200": 303.21532470703124,
      "gap_up": true,
      "close_near_high": true,
      "long_red": false,
      "ticker": "6414",
      "name": "樺漢",
      "industry": "電腦及週邊",
      "industry_strong": true,
      "market_cap_billions": 508.41411584,
      "mcap_pass": true,
      "momentum_score": 95,
      "momentum_notes": [
        "跳空缺口",
        "ATH",
        "族群同步"
      ],
      "tier": "⭐⭐⭐",
      "next_day_prob": "≥85%"
    },
    {
      "today": 145.0,
      "monthly_max_2y": 138.265625,
      "ratio": 1.0487060684823144,
      "from_high_pct": 4.87060684823144,
      "bullish": true,
      "bullish_fast": false,
      "change_pct": 9.84848484848484,
      "vol_ratio": 1.6121352317874786,
      "rsi": 60.35009463466056,
      "ma5": 128.9,
      "ma20": 132.94785270690917,
      "ma60": 122.94564285278321,
      "ma200": 80.24706197738648,
      "gap_up": true,
      "close_near_high": true,
      "long_red": true,
      "ticker": "6166",
      "name": "凌華",
      "industry": "電腦及週邊",
      "industry_strong": true,
      "market_cap_billions": 172.87286784,
      "mcap_pass": true,
      "momentum_score": 95,
      "momentum_notes": [
        "跳空缺口",
        "ATH",
        "族群同步"
      ],
      "tier": "⭐⭐⭐",
      "next_day_prob": "≥85%"
    }
  ]
}