{
  "date": "2026-07-14 15:07",
  "stage": "BULL_MID",
  "label": "⚡ 多頭中段",
  "desc": "強勢但動能轉鈍",
  "notes": [
    "距 MA200 +32.1%（領先牛市）"
  ],
  "indicators": {
    "price": 44737.95,
    "ma60": 43149.14,
    "ma120": 38127.01,
    "ma200": 33875.63,
    "ma87_zheng": 40261.82,
    "ma284_zheng": 30645.42,
    "bias_87_pct": 11.12,
    "bias_284_pct": 45.99,
    "zheng_da_signal": "🟢 鄭大兩線多頭排列（87MA 上 284MA 上）",
    "dist_ma60_pct": 3.68,
    "dist_ma120_pct": 17.34,
    "dist_ma200_pct": 32.07,
    "ret_5d": -3.91,
    "ret_20d": 1.29,
    "ret_60d": 20.48,
    "rsi_daily": 35.8,
    "weekly_K": 70.3,
    "monthly_K": 89.1,
    "monthly_D": 89.8,
    "vol_ratio_20": null,
    "vol_avg_20": 6919280.0
  },
  "playbook": {
    "sector_focus": "取 5 日 TOP 3 強勢族群",
    "cb_filter": "族群中找有 CB 的個股",
    "action": "⚡ 健康牛市：可分批進場強勢族群有 CB 的個股",
    "risk_advice": "滿倉持有，逢回加碼"
  }
}